{
  "balady": [
    {
      "id": 2523,
      "name": "[1000] تقرير في غير فوري (سلامة)",
      "price": 699,
      "category": "خدمات حكومية / بلدي",
      "active": true,
      "sale_ok": true
    },
    {
      "id": 2512,
      "name": "[1002] شهادة تركيب أدوات الوقاية من الحريق (سلامة)",
      "price": 249,
      "category": "خدمات حكومية / بلدي",
      "active": true,
      "sale_ok": true
    },
    {
      "id": 2519,
      "name": "[1008] اعتراض على مخالفة الرقابة",
      "price": 35,
      "category": "خدمات حكومية / بلدي",
      "active": true,
      "sale_ok": true
    },
    {
      "id": 2520,
      "name": "[1009] استخراج ملصق رايك بفرق",
      "price": 35,
      "category": "خدمات حكومية / بلدي",
      "active": true,
      "sale_ok": true
    },
    {
      "id": 2507,
      "name": "[1018] تجديد رخصة بلدية (تجارية)",
      "price": 99,
      "category": "خدمات حكومية / بلدي",
      "active": true,
      "sale_ok": true
    },
    {
      "id": 2513,
      "name": "[1025] تجديد رخصة سلامة (الدفاع المدني)",
      "price": 160,
      "category": "خدمات حكومية / بلدي",
      "active": true,
      "sale_ok": true
    },
    {
      "id": 2516,
      "name": "[1033] قبول ملكية نقل رخصة بلدية (تجارية)",
      "price": 49,
      "category": "خدمات حكومية / بلدي",
      "active": true,
      "sale_ok": true
    },
    {
      "id": 2517,
      "name": "[1034] نقل ملكية رخصة بلدية (تجارية)",
      "price": 199,
      "category": "خدمات حكومية / بلدي",
      "active": true,
      "sale_ok": true
    },
    {
      "id": 2506,
      "name": "[1035] تعديل رخصة بلدية (تجارية)",
      "price": 99,
      "category": "خدمات حكومية / بلدي",
      "active": true,
      "sale_ok": true
    },
    {
      "id": 2524,
      "name": "[1106] تقديم على جهاز نقاط البيع",
      "price": 104.34,
      "category": "خدمات حكومية / بلدي",
      "active": true,
      "sale_ok": true
    },
    {
      "id": 2509,
      "name": "[1107] إصدار رخصة عربة متنقلة (فود تراك)",
      "price": 150,
      "category": "خدمات حكومية / بلدي",
      "active": true,
      "sale_ok": true
    },
    {
      "id": 2508,
      "name": "[938] إصدار رخصة بلدية (تجارية)",
      "price": 199,
      "category": "خدمات حكومية / بلدي",
      "active": true,
      "sale_ok": true
    },
    {
      "id": 2514,
      "name": "[944] إصدار ترخيص سلامة (الدفاع المدني)",
      "price": 199,
      "category": "خدمات حكومية / بلدي",
      "active": true,
      "sale_ok": true
    },
    {
      "id": 2515,
      "name": "[945] إلغاء رخصة بلدي",
      "price": 49,
      "category": "خدمات حكومية / بلدي",
      "active": true,
      "sale_ok": true
    },
    {
      "id": 2518,
      "name": "[948] تقديم إفصاح عن إيراد رسوم مرافق الإيواء",
      "price": 99,
      "category": "خدمات حكومية / بلدي",
      "active": true,
      "sale_ok": true
    },
    {
      "id": 2521,
      "name": "[951] استخراج وتجديد الشهادات الصحية للعمالة",
      "price": 50,
      "category": "خدمات حكومية / بلدي",
      "active": true,
      "sale_ok": true
    },
    {
      "id": 2511,
      "name": "[986] إصدار ترخيص 24  ساعة محل تجاري",
      "price": 99,
      "category": "خدمات حكومية / بلدي",
      "active": true,
      "sale_ok": true
    },
    {
      "id": 2510,
      "name": "[997] إصدار وتجديد رخصة سكن جماعي",
      "price": 150,
      "category": "خدمات حكومية / بلدي",
      "active": true,
      "sale_ok": true
    },
    {
      "id": 2522,
      "name": "[999] تقرير في فوري (سلامة)",
      "price": 549,
      "category": "خدمات حكومية / بلدي",
      "active": true,
      "sale_ok": true
    }
  ],
  "business-establishment": [
    {
      "id": 2559,
      "name": "[1003] اشتراك أو تجديد ابشر أعمال",
      "price": 49,
      "category": "خدمات الأعمال / تأسيس",
      "active": true,
      "sale_ok": true
    },
    {
      "id": 2562,
      "name": "[1007] تقديم افصاح عن ابراد رسوم مرافق الفواء",
      "price": 150,
      "category": "خدمات الأعمال / تأسيس",
      "active": true,
      "sale_ok": true
    },
    {
      "id": 2563,
      "name": "[1010] شهادة توثيق التجارة الالكترونية",
      "price": 100,
      "category": "خدمات الأعمال / تأسيس",
      "active": true,
      "sale_ok": true
    },
    {
      "id": 2564,
      "name": "[1011] الاستعلام عن الطلبات المقدمة",
      "price": 100,
      "category": "خدمات الأعمال / تأسيس",
      "active": true,
      "sale_ok": true
    },
    {
      "id": 2565,
      "name": "[1013] طباعة سجل تجاري",
      "price": 549,
      "category": "خدمات الأعمال / تأسيس",
      "active": true,
      "sale_ok": true
    },
    {
      "id": 2568,
      "name": "[1016] التسجيل في تابي أو تمارا",
      "price": 50,
      "category": "خدمات الأعمال / تأسيس",
      "active": true,
      "sale_ok": true
    },
    {
      "id": 2561,
      "name": "[1039] إضافة مفوض إلكتروني",
      "price": 150,
      "category": "خدمات الأعمال / تأسيس",
      "active": true,
      "sale_ok": true
    },
    {
      "id": 2569,
      "name": "[1104] فتح حساب بنكي تجاري",
      "price": 50,
      "category": "خدمات الأعمال / تأسيس",
      "active": true,
      "sale_ok": true
    },
    {
      "id": 2552,
      "name": "[1153] التقديم على حاضنات الأعمال",
      "price": 60,
      "category": "خدمات الأعمال / تأسيس",
      "active": true,
      "sale_ok": true
    },
    {
      "id": 2567,
      "name": "[1157] ربط الحساب البنكي للمؤسسة مع مدد",
      "price": 699,
      "category": "خدمات الأعمال / تأسيس",
      "active": true,
      "sale_ok": true
    },
    {
      "id": 2560,
      "name": "[1158] تسجيل منشأة في مدد",
      "price": 199,
      "category": "خدمات الأعمال / تأسيس",
      "active": true,
      "sale_ok": true
    },
    {
      "id": 2558,
      "name": "[1159] طباعة تقارير إدارة الرواتب",
      "price": 100,
      "category": "خدمات الأعمال / تأسيس",
      "active": true,
      "sale_ok": true
    },
    {
      "id": 2566,
      "name": "[1163] فتح حساب بنكي للمؤسسة في STC Bank وربطه مع مدد",
      "price": 699,
      "category": "خدمات الأعمال / تأسيس",
      "active": true,
      "sale_ok": true
    },
    {
      "id": 2549,
      "name": "[1304] تسجيل عنوان وطني للمنشآت",
      "price": 100,
      "category": "خدمات الأعمال / تأسيس",
      "active": true,
      "sale_ok": true
    },
    {
      "id": 2551,
      "name": "[1350] تسجيل منشأة في ضريبة القيمة المضافة / رقم ضريبي جديد",
      "price": 60,
      "category": "خدمات الأعمال / تأسيس",
      "active": true,
      "sale_ok": true
    },
    {
      "id": 2548,
      "name": "[987] اصدار السجل التجاري للمؤسسات",
      "price": 99,
      "category": "خدمات الأعمال / تأسيس",
      "active": true,
      "sale_ok": true
    },
    {
      "id": 2550,
      "name": "[989] حجز / تمديد / الغاء اسم تجاري",
      "price": 100,
      "category": "خدمات الأعمال / تأسيس",
      "active": true,
      "sale_ok": true
    },
    {
      "id": 2553,
      "name": "[992] اصدار ترخيص سلامة (الدفاع المدني)",
      "price": 30,
      "category": "خدمات الأعمال / تأسيس",
      "active": true,
      "sale_ok": true
    },
    {
      "id": 2554,
      "name": "[993] فتح حساب وتفعيل منصة قوى",
      "price": 30,
      "category": "خدمات الأعمال / تأسيس",
      "active": true,
      "sale_ok": true
    },
    {
      "id": 2555,
      "name": "[995] اصدار ترخيص بلدية (تجارية)",
      "price": 85,
      "category": "خدمات الأعمال / تأسيس",
      "active": true,
      "sale_ok": true
    },
    {
      "id": 2556,
      "name": "[996] إصدار رخصة غرفة متنقلة (فود تراك)",
      "price": 150,
      "category": "خدمات الأعمال / تأسيس",
      "active": true,
      "sale_ok": true
    },
    {
      "id": 2557,
      "name": "[998] فتح ملف منشأة (السجلات التجارية والزراعية)",
      "price": 199,
      "category": "خدمات الأعمال / تأسيس",
      "active": true,
      "sale_ok": true
    }
  ],
  "business-renewal": [
    {
      "id": 2571,
      "name": "[1023] تجديد السجل التجاري للمؤسسات",
      "price": 150,
      "category": "خدمات الأعمال / تجديد",
      "active": true,
      "sale_ok": true
    },
    {
      "id": 2572,
      "name": "[1024] اشتراك او تجديد ابشر أعمال",
      "price": 99,
      "category": "خدمات الأعمال / تجديد",
      "active": true,
      "sale_ok": true
    },
    {
      "id": 2573,
      "name": "[1026] إصدار شهادة الالتزام بالنظام وحماية الأجور",
      "price": 100,
      "category": "خدمات الأعمال / تجديد",
      "active": true,
      "sale_ok": true
    },
    {
      "id": 2574,
      "name": "[1160] طباعة تقرير حماية الأجور",
      "price": 50,
      "category": "خدمات الأعمال / تجديد",
      "active": true,
      "sale_ok": true
    },
    {
      "id": 2575,
      "name": "[1161] رفع مسير رواتب الموظفين الشهرية في مدد",
      "price": 50,
      "category": "خدمات الأعمال / تجديد",
      "active": true,
      "sale_ok": true
    },
    {
      "id": 2570,
      "name": "[1349] تقديم الإقرارات الضريبية",
      "price": 150,
      "category": "خدمات الأعمال / تجديد",
      "active": true,
      "sale_ok": true
    }
  ],
  "business-transfer": [
    {
      "id": 2576,
      "name": "[1032] تعديل بيانات منشأة",
      "price": 100,
      "category": "خدمات الأعمال / تعديل ونقل",
      "active": true,
      "sale_ok": true
    },
    {
      "id": 2577,
      "name": "[1036] نقل السجل التجاري للمؤسسات",
      "price": 199,
      "category": "خدمات الأعمال / تعديل ونقل",
      "active": true,
      "sale_ok": true
    },
    {
      "id": 2578,
      "name": "[1037] تعديل السجل التجاري للمؤسسات",
      "price": 199,
      "category": "خدمات الأعمال / تعديل ونقل",
      "active": true,
      "sale_ok": true
    },
    {
      "id": 2579,
      "name": "[1040] تغيير نشاط منشأة",
      "price": 100,
      "category": "خدمات الأعمال / تعديل ونقل",
      "active": true,
      "sale_ok": true
    }
  ],
  "business-employees": [
    {
      "id": 2544,
      "name": "[1038] إصدار شهادة السعودة",
      "price": 99,
      "category": "خدمات الأعمال / موظفين",
      "active": true,
      "sale_ok": true
    },
    {
      "id": 2531,
      "name": "[1177] استخراج تأشيرة العمالة الزراعية",
      "price": 149,
      "category": "خدمات الأعمال / موظفين",
      "active": true,
      "sale_ok": true
    },
    {
      "id": 2536,
      "name": "[1227] نقل تابع للمنشأة",
      "price": 50,
      "category": "خدمات الأعمال / موظفين",
      "active": true,
      "sale_ok": true
    },
    {
      "id": 2537,
      "name": "[1229] نقل كفالة عامل للمنشأة",
      "price": 50,
      "category": "خدمات الأعمال / موظفين",
      "active": true,
      "sale_ok": true
    },
    {
      "id": 2540,
      "name": "[1233] تعديل المهنة",
      "price": 99,
      "category": "خدمات الأعمال / موظفين",
      "active": true,
      "sale_ok": true
    },
    {
      "id": 2541,
      "name": "[1234] إلغاء التأشيرات للعمال",
      "price": 50,
      "category": "خدمات الأعمال / موظفين",
      "active": true,
      "sale_ok": true
    },
    {
      "id": 2543,
      "name": "[1236] إصدار / تجديد رخصة عمل",
      "price": 50,
      "category": "خدمات الأعمال / موظفين",
      "active": true,
      "sale_ok": true
    },
    {
      "id": 2535,
      "name": "[1238] نقل عامل بين الفروع",
      "price": 50,
      "category": "خدمات الأعمال / موظفين",
      "active": true,
      "sale_ok": true
    },
    {
      "id": 2547,
      "name": "[1243] تصحيح المهنة",
      "price": 50,
      "category": "خدمات الأعمال / موظفين",
      "active": true,
      "sale_ok": true
    },
    {
      "id": 2532,
      "name": "[964] إصدار / تمديد / تأشيرة الخروج والعودة",
      "price": 50,
      "category": "خدمات الأعمال / موظفين",
      "active": true,
      "sale_ok": true
    },
    {
      "id": 2533,
      "name": "[966] تأمين طبي",
      "price": 52.1,
      "category": "خدمات الأعمال / موظفين",
      "active": true,
      "sale_ok": true
    },
    {
      "id": 2534,
      "name": "[967] إصدار تأشيرة دائمة أو مؤقتة",
      "price": 50,
      "category": "خدمات الأعمال / موظفين",
      "active": true,
      "sale_ok": true
    },
    {
      "id": 2538,
      "name": "[971] توليق عقد الموظفين",
      "price": 0,
      "category": "خدمات الأعمال / موظفين",
      "active": true,
      "sale_ok": true
    },
    {
      "id": 2539,
      "name": "[972] إضافة موظفين على مدد",
      "price": 99,
      "category": "خدمات الأعمال / موظفين",
      "active": true,
      "sale_ok": true
    },
    {
      "id": 2542,
      "name": "[975] بلاغ إقطاع عن العمال (بلاغ الهروب)",
      "price": 50,
      "category": "خدمات الأعمال / موظفين",
      "active": true,
      "sale_ok": true
    },
    {
      "id": 2545,
      "name": "[982] إلغاء تأشيرة الخروج النهائي",
      "price": 99,
      "category": "خدمات الأعمال / موظفين",
      "active": true,
      "sale_ok": true
    },
    {
      "id": 2546,
      "name": "[983] إلغاء تأشيرة الخروج والعودة",
      "price": 99,
      "category": "خدمات الأعمال / موظفين",
      "active": true,
      "sale_ok": true
    }
  ],
  "chamber": [
    {
      "id": 2580,
      "name": "[1041] التسجيل في الغرفة التجارية",
      "price": 80,
      "category": "خدمات حكومية / الغرفة التجارية",
      "active": true,
      "sale_ok": true
    },
    {
      "id": 2581,
      "name": "[1042] تصديق الوثائق في الغرفة التجارية",
      "price": 80,
      "category": "خدمات حكومية / الغرفة التجارية",
      "active": true,
      "sale_ok": true
    },
    {
      "id": 2582,
      "name": "[1043] تجديد العضوية في الغرفة التجارية",
      "price": 80,
      "category": "خدمات حكومية / الغرفة التجارية",
      "active": true,
      "sale_ok": true
    },
    {
      "id": 2583,
      "name": "[1044] استخراج شهادة عضوية الغرفة التجارية",
      "price": 80,
      "category": "خدمات حكومية / الغرفة التجارية",
      "active": true,
      "sale_ok": true
    }
  ],
  "discounts": [
    {
      "id": 2584,
      "name": "[1045] تسجيل فرع جديد في نظام التخفيضات",
      "price": 100,
      "category": "خدمات حكومية / التخفيضات",
      "active": true,
      "sale_ok": true
    },
    {
      "id": 2585,
      "name": "[1046] إعداد وتدقيق قوائم المنتجات",
      "price": 150,
      "category": "خدمات حكومية / التخفيضات",
      "active": true,
      "sale_ok": true
    },
    {
      "id": 2586,
      "name": "[1047] التقديم على التخفيضات الموسمية",
      "price": 120,
      "category": "خدمات حكومية / التخفيضات",
      "active": true,
      "sale_ok": true
    },
    {
      "id": 2587,
      "name": "[1048] إصدار ترخيص تخفيضات",
      "price": 200,
      "category": "خدمات حكومية / التخفيضات",
      "active": true,
      "sale_ok": true
    },
    {
      "id": 2588,
      "name": "[1049] إدارة الرصيد السنوي للتخفيضات",
      "price": 130,
      "category": "خدمات حكومية / التخفيضات",
      "active": true,
      "sale_ok": true
    }
  ],
  "education-services": [
    {
      "id": 2591,
      "name": "[1050] التسجيل في الجامعات والكليات والمعاهد السعودية",
      "price": 75,
      "category": "خدمات الأفراد / التعليم",
      "active": true,
      "sale_ok": true
    },
    {
      "id": 2592,
      "name": "[1051] طلب انسحاب طالب من الجامعة",
      "price": 75,
      "category": "خدمات الأفراد / التعليم",
      "active": true,
      "sale_ok": true
    },
    {
      "id": 2596,
      "name": "[1052] حساب النسبة الموزونة للقبول في الجامعات",
      "price": 150,
      "category": "خدمات الأفراد / التعليم",
      "active": true,
      "sale_ok": true
    },
    {
      "id": 2597,
      "name": "[1053] تعديل الجدول الجامعي",
      "price": 100,
      "category": "خدمات الأفراد / التعليم",
      "active": true,
      "sale_ok": true
    },
    {
      "id": 2598,
      "name": "[1054] تحويل الملفات",
      "price": 100,
      "category": "خدمات الأفراد / التعليم",
      "active": true,
      "sale_ok": true
    },
    {
      "id": 2599,
      "name": "[1055] حل واجب لكل المنصات",
      "price": 50,
      "category": "خدمات الأفراد / التعليم",
      "active": true,
      "sale_ok": true
    },
    {
      "id": 2602,
      "name": "[1058] التسجيل في دورات معهد الإدارة العامة",
      "price": 20,
      "category": "خدمات الأفراد / التعليم",
      "active": true,
      "sale_ok": true
    },
    {
      "id": 2603,
      "name": "[1059] إصدار الرخصة المهنية للمعلمين",
      "price": 20,
      "category": "خدمات الأفراد / التعليم",
      "active": true,
      "sale_ok": true
    },
    {
      "id": 2604,
      "name": "[1060] حجز موعد لاختبار الرخصة المهنية للمعلمين",
      "price": 40,
      "category": "خدمات الأفراد / التعليم",
      "active": true,
      "sale_ok": true
    },
    {
      "id": 2609,
      "name": "[1065] فتح حساب ولي أمر على نور",
      "price": 50,
      "category": "خدمات الأفراد / التعليم",
      "active": true,
      "sale_ok": true
    },
    {
      "id": 2610,
      "name": "[1071] إعداد حساب روضتي",
      "price": 25,
      "category": "خدمات الأفراد / التعليم",
      "active": true,
      "sale_ok": true
    },
    {
      "id": 2600,
      "name": "[1212] تسجيل طالب جديد",
      "price": 50,
      "category": "خدمات الأفراد / التعليم",
      "active": true,
      "sale_ok": true
    },
    {
      "id": 2589,
      "name": "[1213] نقل طالب من مدرسة إلى مدرسة",
      "price": 50,
      "category": "خدمات الأفراد / التعليم",
      "active": true,
      "sale_ok": true
    },
    {
      "id": 2590,
      "name": "[1214] تسجيل الطلبة في المرحلة الابتدائية",
      "price": 50,
      "category": "خدمات الأفراد / التعليم",
      "active": true,
      "sale_ok": true
    },
    {
      "id": 2593,
      "name": "[1215] تسجيل طالب جديد (أجنبي)",
      "price": 49,
      "category": "خدمات الأفراد / التعليم",
      "active": true,
      "sale_ok": true
    },
    {
      "id": 2594,
      "name": "[1216] تسجيل طالب في النقل الدراسي (رافد)",
      "price": 49,
      "category": "خدمات الأفراد / التعليم",
      "active": true,
      "sale_ok": true
    },
    {
      "id": 2608,
      "name": "[1217] تسجيل خطة النشاط في منصة نور (فصل كامل)",
      "price": 50,
      "category": "خدمات الأفراد / التعليم",
      "active": true,
      "sale_ok": true
    },
    {
      "id": 2601,
      "name": "[1218] الاستعلام عن نتائج الطلاب",
      "price": 50,
      "category": "خدمات الأفراد / التعليم",
      "active": true,
      "sale_ok": true
    },
    {
      "id": 2611,
      "name": "[1219] تسجيل الطلاب في رياض الأطفال",
      "price": 80,
      "category": "خدمات الأفراد / التعليم",
      "active": true,
      "sale_ok": true
    },
    {
      "id": 2605,
      "name": "[1220] التسجيل في نظام فارس للمعلمين",
      "price": 40,
      "category": "خدمات الأفراد / التعليم",
      "active": true,
      "sale_ok": true
    },
    {
      "id": 2606,
      "name": "[1221] طلب إجازة للمعلمين والمعلمات",
      "price": 30,
      "category": "خدمات الأفراد / التعليم",
      "active": true,
      "sale_ok": true
    },
    {
      "id": 2607,
      "name": "[1222] طلب تعريف بالراتب للمعلمين والمعلمات",
      "price": 30,
      "category": "خدمات الأفراد / التعليم",
      "active": true,
      "sale_ok": true
    },
    {
      "id": 2595,
      "name": "[1436] تسجيل الطالب في الصف الأول الابتدائي",
      "price": 150,
      "category": "خدمات الأفراد / التعليم",
      "active": true,
      "sale_ok": true
    }
  ],
  "absher": [
    {
      "id": 2493,
      "name": "[1057] تعديل المؤهل الدراسي في الأحوال المدنية",
      "price": 25,
      "category": "خدمات حكومية / أبشر",
      "active": true,
      "sale_ok": true
    },
    {
      "id": 2480,
      "name": "[910] الغاء تأشيرة الخروج والعودة",
      "price": 49,
      "category": "خدمات حكومية / أبشر",
      "active": true,
      "sale_ok": true
    },
    {
      "id": 2481,
      "name": "[911] اشتراك أو تجديد أبشر أعمال",
      "price": 49,
      "category": "خدمات حكومية / أبشر",
      "active": true,
      "sale_ok": true
    },
    {
      "id": 2484,
      "name": "[914] إصدار / تمديد تأشيرة الخروج والعودة",
      "price": 50,
      "category": "خدمات حكومية / أبشر",
      "active": true,
      "sale_ok": true
    },
    {
      "id": 2488,
      "name": "[918] الغاء تأشيرة الخروج النهائي",
      "price": 49,
      "category": "خدمات حكومية / أبشر",
      "active": true,
      "sale_ok": true
    },
    {
      "id": 2490,
      "name": "[920] تقديم طلب تواصل",
      "price": 50,
      "category": "خدمات حكومية / أبشر",
      "active": true,
      "sale_ok": true
    },
    {
      "id": 2491,
      "name": "[921] تجديد استمارات السيارات",
      "price": 50,
      "category": "خدمات حكومية / أبشر",
      "active": true,
      "sale_ok": true
    },
    {
      "id": 2492,
      "name": "[922] تجديد الهوية الوطنية",
      "price": 50,
      "category": "خدمات حكومية / أبشر",
      "active": true,
      "sale_ok": true
    },
    {
      "id": 2494,
      "name": "[924] التسجيل في أبشر أفراد/أعمال",
      "price": 50,
      "category": "خدمات حكومية / أبشر",
      "active": true,
      "sale_ok": true
    },
    {
      "id": 2495,
      "name": "[925] الاستعلام عن المخالفات المرورية",
      "price": 17.3,
      "category": "خدمات حكومية / أبشر",
      "active": true,
      "sale_ok": true
    },
    {
      "id": 2496,
      "name": "[926] نقل ملكية المركبة بين أفراد الأسرة",
      "price": 50,
      "category": "خدمات حكومية / أبشر",
      "active": true,
      "sale_ok": true
    },
    {
      "id": 2497,
      "name": "[927] نقل ملكية المركبة فوري",
      "price": 99,
      "category": "خدمات حكومية / أبشر",
      "active": true,
      "sale_ok": true
    },
    {
      "id": 2499,
      "name": "[929] تجديد رخصة القيادة",
      "price": 50,
      "category": "خدمات حكومية / أبشر",
      "active": true,
      "sale_ok": true
    },
    {
      "id": 2500,
      "name": "[930] طلب هوية وطنية بدل فاقد",
      "price": 50,
      "category": "خدمات حكومية / أبشر",
      "active": true,
      "sale_ok": true
    },
    {
      "id": 2501,
      "name": "[931] تحديث البيانات على منصة أبشر",
      "price": 50,
      "category": "خدمات حكومية / أبشر",
      "active": true,
      "sale_ok": true
    },
    {
      "id": 2502,
      "name": "[932] تجديد جواز السفر السعودي",
      "price": 50,
      "category": "خدمات حكومية / أبشر",
      "active": true,
      "sale_ok": true
    },
    {
      "id": 2503,
      "name": "[933] إصدار جواز سفر سعودي جديد",
      "price": 50,
      "category": "خدمات حكومية / أبشر",
      "active": true,
      "sale_ok": true
    },
    {
      "id": 2504,
      "name": "[934] الاعتراض على المخالفات المرورية",
      "price": 50,
      "category": "خدمات حكومية / أبشر",
      "active": true,
      "sale_ok": true
    },
    {
      "id": 2505,
      "name": "[935] تسجيل المواليد",
      "price": 150,
      "category": "خدمات حكومية / أبشر",
      "active": true,
      "sale_ok": true
    },
    {
      "id": 2482,
      "name": "[962] نقل الكفالة",
      "price": 50,
      "category": "خدمات حكومية / أبشر",
      "active": true,
      "sale_ok": true
    },
    {
      "id": 2483,
      "name": "[963] إصدار تأشيرة الخروج النهائي",
      "price": 50,
      "category": "خدمات حكومية / أبشر",
      "active": true,
      "sale_ok": true
    },
    {
      "id": 2485,
      "name": "[965] إصدار / تجديد إقامة",
      "price": 50,
      "category": "خدمات حكومية / أبشر",
      "active": true,
      "sale_ok": true
    },
    {
      "id": 2498,
      "name": "[978] تعديل المهنة في أبشر أفراد/أعمال",
      "price": 50,
      "category": "خدمات حكومية / أبشر",
      "active": true,
      "sale_ok": true
    },
    {
      "id": 2487,
      "name": "[979] طلب تقرير مقيم",
      "price": 49,
      "category": "خدمات حكومية / أبشر",
      "active": true,
      "sale_ok": true
    },
    {
      "id": 2489,
      "name": "[981] تحديث معلومات الجواز للمقيمين",
      "price": 100,
      "category": "خدمات حكومية / أبشر",
      "active": true,
      "sale_ok": true
    },
    {
      "id": 2486,
      "name": "[985] بلاغ تغيب عن العمل",
      "price": 49,
      "category": "خدمات حكومية / أبشر",
      "active": true,
      "sale_ok": true
    }
  ],
  "ejar": [
    {
      "id": 2613,
      "name": "[1075] إنشاء عقد إيجار سكني مع إحضار صك ملكية ومؤجر",
      "price": 300,
      "category": "خدمات حكومية / إيجار",
      "active": true,
      "sale_ok": true
    },
    {
      "id": 2614,
      "name": "[1076] عمل عقد أيجار تجاري",
      "price": 400,
      "category": "خدمات حكومية / إيجار",
      "active": true,
      "sale_ok": true
    },
    {
      "id": 2615,
      "name": "[1077] عمل عقد أيجار تجاري من الباطن",
      "price": 400,
      "category": "خدمات حكومية / إيجار",
      "active": true,
      "sale_ok": true
    },
    {
      "id": 2616,
      "name": "[1078] إنهاء عقد تجاري أو سكني",
      "price": 50,
      "category": "خدمات حكومية / إيجار",
      "active": true,
      "sale_ok": true
    },
    {
      "id": 2617,
      "name": "[1079] استخراج رخصة مسوق عقاري",
      "price": 50,
      "category": "خدمات حكومية / إيجار",
      "active": true,
      "sale_ok": true
    },
    {
      "id": 2618,
      "name": "[1080] تجديد / تعديل عقد الإيجار",
      "price": 50,
      "category": "خدمات حكومية / إيجار",
      "active": true,
      "sale_ok": true
    },
    {
      "id": 2619,
      "name": "[1081] طباعة عقد الإيجار",
      "price": 50,
      "category": "خدمات حكومية / إيجار",
      "active": true,
      "sale_ok": true
    },
    {
      "id": 2612,
      "name": "[1468] إنشاء عقد إيجار سكني",
      "price": 300,
      "category": "خدمات حكومية / إيجار",
      "active": true,
      "sale_ok": true
    }
  ],
  "electricity": [
    {
      "id": 2620,
      "name": "[1082] نقل ملكية عداد كهرباء",
      "price": 49,
      "category": "خدمات حكومية / الكهرباء",
      "active": true,
      "sale_ok": true
    },
    {
      "id": 2621,
      "name": "[1083] طلب عداد كهرباء",
      "price": 49,
      "category": "خدمات حكومية / الكهرباء",
      "active": true,
      "sale_ok": true
    },
    {
      "id": 2622,
      "name": "[1084] طلب (تغيير / إزالة) عداد",
      "price": 49,
      "category": "خدمات حكومية / الكهرباء",
      "active": true,
      "sale_ok": true
    },
    {
      "id": 2623,
      "name": "[1085] طلب نقل عداد",
      "price": 49,
      "category": "خدمات حكومية / الكهرباء",
      "active": true,
      "sale_ok": true
    },
    {
      "id": 2624,
      "name": "[1086] طلب توثيق عداد",
      "price": 49,
      "category": "خدمات حكومية / الكهرباء",
      "active": true,
      "sale_ok": true
    },
    {
      "id": 2625,
      "name": "[1087] دفع فاتورة الكهرباء",
      "price": 20,
      "category": "خدمات حكومية / الكهرباء",
      "active": true,
      "sale_ok": true
    },
    {
      "id": 2626,
      "name": "[1088] طلب إزالة معدة",
      "price": 35,
      "category": "خدمات حكومية / الكهرباء",
      "active": true,
      "sale_ok": true
    },
    {
      "id": 2627,
      "name": "[1089] طلب عداد إضافي",
      "price": 49,
      "category": "خدمات حكومية / الكهرباء",
      "active": true,
      "sale_ok": true
    }
  ],
  "engineering-consulting": [
    {
      "id": 2628,
      "name": "[1090] استشارات دراسة وتدقيق المخططات",
      "price": 500,
      "category": "خدمات متخصصة / استشارات هندسية",
      "active": true,
      "sale_ok": true
    },
    {
      "id": 2629,
      "name": "[1091] التحكيم وفض النزاعات الهندسية",
      "price": 500,
      "category": "خدمات متخصصة / استشارات هندسية",
      "active": true,
      "sale_ok": true
    },
    {
      "id": 2630,
      "name": "[1092] استشارات ترشيد تكاليف البناء",
      "price": 800,
      "category": "خدمات متخصصة / استشارات هندسية",
      "active": true,
      "sale_ok": true
    },
    {
      "id": 2631,
      "name": "[1093] الإشراف الفني العالي (زيارات ميدانية)",
      "price": 800,
      "category": "خدمات متخصصة / استشارات هندسية",
      "active": true,
      "sale_ok": true
    },
    {
      "id": 2632,
      "name": "[1094] فحص واستلام العقار",
      "price": 600,
      "category": "خدمات متخصصة / استشارات هندسية",
      "active": true,
      "sale_ok": true
    },
    {
      "id": 2633,
      "name": "[1095] إعداد جداول الكميات والمواصفات",
      "price": 600,
      "category": "خدمات متخصصة / استشارات هندسية",
      "active": true,
      "sale_ok": true
    },
    {
      "id": 2634,
      "name": "[1096] اعتماد المخططات والامتثال",
      "price": 700,
      "category": "خدمات متخصصة / استشارات هندسية",
      "active": true,
      "sale_ok": true
    },
    {
      "id": 2635,
      "name": "[1097] التصميم الداخلي المعماري",
      "price": 700,
      "category": "خدمات متخصصة / استشارات هندسية",
      "active": true,
      "sale_ok": true
    },
    {
      "id": 2636,
      "name": "[1098] إعادة تطوير المباني القائمة",
      "price": 450,
      "category": "خدمات متخصصة / استشارات هندسية",
      "active": true,
      "sale_ok": true
    }
  ],
  "fasah": [
    {
      "id": 2637,
      "name": "[1099] إنشاء وتفعيل حساب المنشأة",
      "price": 100,
      "category": "خدمات حكومية / فسح",
      "active": true,
      "sale_ok": true
    },
    {
      "id": 2638,
      "name": "[1100] إصدار وتجديد التفاويض الإلكترونية",
      "price": 180,
      "category": "خدمات حكومية / فسح",
      "active": true,
      "sale_ok": true
    },
    {
      "id": 2639,
      "name": "[1101] تقديم خطابات التعديل الإلكترونية",
      "price": 150,
      "category": "خدمات حكومية / فسح",
      "active": true,
      "sale_ok": true
    },
    {
      "id": 2640,
      "name": "[1102] تصدير بيانات الصادرات والواردات",
      "price": 200,
      "category": "خدمات حكومية / فسح",
      "active": true,
      "sale_ok": true
    }
  ],
  "freelance": [
    {
      "id": 2641,
      "name": "[1103] التسجيل في تابي أو تمارة",
      "price": 75,
      "category": "خدمات الأعمال / العمل الحر",
      "active": true,
      "sale_ok": true
    },
    {
      "id": 2642,
      "name": "[1105] شهادة توثيق التجارة الإلكترونية",
      "price": 100,
      "category": "خدمات الأعمال / العمل الحر",
      "active": true,
      "sale_ok": true
    },
    {
      "id": 2643,
      "name": "[1108] وثيقة عمل حر",
      "price": 35,
      "category": "خدمات الأعمال / العمل الحر",
      "active": true,
      "sale_ok": true
    }
  ],
  "gosi": [
    {
      "id": 2662,
      "name": "[1109] إصدار شهادة مدد الأجور",
      "price": 35,
      "category": "خدمات حكومية / التأمينات",
      "active": true,
      "sale_ok": true
    },
    {
      "id": 2663,
      "name": "[1110] التحقق من الاشتراك في التأمينات",
      "price": 50,
      "category": "خدمات حكومية / التأمينات",
      "active": true,
      "sale_ok": true
    },
    {
      "id": 2664,
      "name": "[1111] صرف مستحقات العجز غير المهني",
      "price": 50,
      "category": "خدمات حكومية / التأمينات",
      "active": true,
      "sale_ok": true
    },
    {
      "id": 2665,
      "name": "[1112] طلب صرف الراتب التقاعدي للورثة",
      "price": 85,
      "category": "خدمات حكومية / التأمينات",
      "active": true,
      "sale_ok": true
    },
    {
      "id": 2666,
      "name": "[1113] تحديث الحساب البنكي للمستفيد في التأمينات",
      "price": 35,
      "category": "خدمات حكومية / التأمينات",
      "active": true,
      "sale_ok": true
    },
    {
      "id": 2667,
      "name": "[1114] طلب إضافة فرد غير مسجل في التأمينات الاجتماعية",
      "price": 50,
      "category": "خدمات حكومية / التأمينات",
      "active": true,
      "sale_ok": true
    },
    {
      "id": 2668,
      "name": "[1115] طباعة مشهد راتب متقاعد",
      "price": 50,
      "category": "خدمات حكومية / التأمينات",
      "active": true,
      "sale_ok": true
    },
    {
      "id": 2669,
      "name": "[1116] طباعة شهادة تأمينات",
      "price": 35,
      "category": "خدمات حكومية / التأمينات",
      "active": true,
      "sale_ok": true
    },
    {
      "id": 2670,
      "name": "[1117] تقديم بلاغ عجز مهني",
      "price": 80,
      "category": "خدمات حكومية / التأمينات",
      "active": true,
      "sale_ok": true
    },
    {
      "id": 2671,
      "name": "[1118] تعديل راتب الموظف",
      "price": 35,
      "category": "خدمات حكومية / التأمينات",
      "active": true,
      "sale_ok": true
    },
    {
      "id": 2672,
      "name": "[1119] إصدار شهادة التزام التأمينات الاجتماعية للمنشأة",
      "price": 45,
      "category": "خدمات حكومية / التأمينات",
      "active": true,
      "sale_ok": true
    },
    {
      "id": 2673,
      "name": "[1120] إصدار شهادة الراتب لموظف",
      "price": 50,
      "category": "خدمات حكومية / التأمينات",
      "active": true,
      "sale_ok": true
    },
    {
      "id": 2674,
      "name": "[1121] توثيق عقود المشتركين",
      "price": 50,
      "category": "خدمات حكومية / التأمينات",
      "active": true,
      "sale_ok": true
    },
    {
      "id": 2675,
      "name": "[1122] إصدار شهادة التزام",
      "price": 35,
      "category": "خدمات حكومية / التأمينات",
      "active": true,
      "sale_ok": true
    },
    {
      "id": 2676,
      "name": "[1123] إضافة أو استبعاد مشترك سعودي",
      "price": 99,
      "category": "خدمات حكومية / التأمينات",
      "active": true,
      "sale_ok": true
    },
    {
      "id": 2677,
      "name": "[1124] تبليغ عن إصابة عمل",
      "price": 75,
      "category": "خدمات حكومية / التأمينات",
      "active": true,
      "sale_ok": true
    },
    {
      "id": 2678,
      "name": "[1125] إضافة أو استبعاد موظف غير سعودي",
      "price": 99,
      "category": "خدمات حكومية / التأمينات",
      "active": true,
      "sale_ok": true
    }
  ],
  "ip": [
    {
      "id": 2681,
      "name": "[1126] إيداع طلب براءة اختراع",
      "price": 300,
      "category": "خدمات متخصصة / الملكية الفكرية",
      "active": true,
      "sale_ok": true
    },
    {
      "id": 2682,
      "name": "[1127] تسجيل علامة تجارية",
      "price": 300,
      "category": "خدمات متخصصة / الملكية الفكرية",
      "active": true,
      "sale_ok": true
    },
    {
      "id": 2683,
      "name": "[1128] تجديد العلامة التجارية",
      "price": 250,
      "category": "خدمات متخصصة / الملكية الفكرية",
      "active": true,
      "sale_ok": true
    },
    {
      "id": 2684,
      "name": "[1129] تسجيل مصنفات حقوق المؤلف",
      "price": 250,
      "category": "خدمات متخصصة / الملكية الفكرية",
      "active": true,
      "sale_ok": true
    },
    {
      "id": 2685,
      "name": "[1130] إيداع طلب تصميم صناعي",
      "price": 150,
      "category": "خدمات متخصصة / الملكية الفكرية",
      "active": true,
      "sale_ok": true
    },
    {
      "id": 2686,
      "name": "[1131] تسجيل التصاميم التخطيطية للدارات المتكاملة",
      "price": 150,
      "category": "خدمات متخصصة / الملكية الفكرية",
      "active": true,
      "sale_ok": true
    },
    {
      "id": 2687,
      "name": "[1132] ترخيص وكيل الملكية الفكرية",
      "price": 200,
      "category": "خدمات متخصصة / الملكية الفكرية",
      "active": true,
      "sale_ok": true
    },
    {
      "id": 2688,
      "name": "[1133] تقديم شكوى انتهاك حقوق الملكية الفكرية",
      "price": 200,
      "category": "خدمات متخصصة / الملكية الفكرية",
      "active": true,
      "sale_ok": true
    }
  ],
  "jobs-services": [
    {
      "id": 2689,
      "name": "[1134] التقديم على وظائف منصة بيت كوم",
      "price": 40,
      "category": "خدمات الأفراد / الوظائف",
      "active": true,
      "sale_ok": true
    },
    {
      "id": 2690,
      "name": "[1135] التقديم على وظائف منصة صبار",
      "price": 40,
      "category": "خدمات الأفراد / الوظائف",
      "active": true,
      "sale_ok": true
    },
    {
      "id": 2691,
      "name": "[1136] التقديم على وظائف منصة مرن",
      "price": 40,
      "category": "خدمات الأفراد / الوظائف",
      "active": true,
      "sale_ok": true
    },
    {
      "id": 2692,
      "name": "[1137] التقديم على الوظائف الحكومية (جدارات)",
      "price": 40,
      "category": "خدمات الأفراد / الوظائف",
      "active": true,
      "sale_ok": true
    },
    {
      "id": 2693,
      "name": "[1138] التسجيل في وظائف طاقات",
      "price": 40,
      "category": "خدمات الأفراد / الوظائف",
      "active": true,
      "sale_ok": true
    },
    {
      "id": 2694,
      "name": "[1139] التقديم على الوظائف العسكرية",
      "price": 40,
      "category": "خدمات الأفراد / الوظائف",
      "active": true,
      "sale_ok": true
    },
    {
      "id": 2695,
      "name": "[1140] التقديم على وظائف تطبيق أسعى",
      "price": 40,
      "category": "خدمات الأفراد / الوظائف",
      "active": true,
      "sale_ok": true
    }
  ],
  "general-services": [
    {
      "id": 2647,
      "name": "[1141] تأمين طبي",
      "price": 52,
      "category": "خدمات عامة",
      "active": true,
      "sale_ok": true
    },
    {
      "id": 2644,
      "name": "[1574] الاستعلام عن السجلات التجارية على اسمك",
      "price": 25.8,
      "category": "خدمات عامة",
      "active": true,
      "sale_ok": true
    },
    {
      "id": 2645,
      "name": "[1575] الاستعلام عن المخالفات المرورية",
      "price": 17.3,
      "category": "خدمات عامة",
      "active": true,
      "sale_ok": true
    },
    {
      "id": 2646,
      "name": "[1576] تصميم سيرة ذاتية احترافية (CV) عربي وإنجليزي",
      "price": 173.5,
      "category": "خدمات عامة",
      "active": true,
      "sale_ok": true
    },
    {
      "id": 2648,
      "name": "[1578] فتح حساب بنكي أفراد / قاصر / تابع",
      "price": 69.56,
      "category": "خدمات عامة",
      "active": true,
      "sale_ok": true
    },
    {
      "id": 2651,
      "name": "[1581] حجز موعد في جميع الجهات الحكومية والخاصة",
      "price": 21.739,
      "category": "خدمات عامة",
      "active": true,
      "sale_ok": true
    },
    {
      "id": 2653,
      "name": "[1583] حجز موعد فحص المركبات (الفحص الدوري)",
      "price": 21.73,
      "category": "خدمات عامة",
      "active": true,
      "sale_ok": true
    },
    {
      "id": 2654,
      "name": "[1584] حجز موعد الجوازات والإقامة",
      "price": 21.73,
      "category": "خدمات عامة",
      "active": true,
      "sale_ok": true
    },
    {
      "id": 2649,
      "name": "[1639] استخراج وثيقة عائلية / بطاقة هوية",
      "price": 104,
      "category": "خدمات عامة",
      "active": true,
      "sale_ok": true
    },
    {
      "id": 2650,
      "name": "[1640] الاستعلام عن صحة الإقامة وتاريخ انتهائها",
      "price": 17.39,
      "category": "خدمات عامة",
      "active": true,
      "sale_ok": true
    },
    {
      "id": 2652,
      "name": "[1642] حجز موعد في المستشفيات والعيادات الحكومية",
      "price": 21.73,
      "category": "خدمات عامة",
      "active": true,
      "sale_ok": true
    },
    {
      "id": 2656,
      "name": "[1646] حجز موعد المحاكم وكتابات العدل",
      "price": 21.73,
      "category": "خدمات عامة",
      "active": true,
      "sale_ok": true
    },
    {
      "id": 2657,
      "name": "[1647] حجز تذاكر طيران داخلية وخارجية",
      "price": 30.43,
      "category": "خدمات عامة",
      "active": true,
      "sale_ok": true
    },
    {
      "id": 2658,
      "name": "[1648] حجز فنادق داخل المملكة وخارجها",
      "price": 30.43,
      "category": "خدمات عامة",
      "active": true,
      "sale_ok": true
    },
    {
      "id": 2660,
      "name": "[1650] حجز تذاكر باصات سفر داخل المملكة",
      "price": 30.43,
      "category": "خدمات عامة",
      "active": true,
      "sale_ok": true
    },
    {
      "id": 2661,
      "name": "[1651] حجز رحلات بحرية وسياحية",
      "price": 130.43,
      "category": "خدمات عامة",
      "active": true,
      "sale_ok": true
    }
  ],
  "ministry-industry": [
    {
      "id": 2712,
      "name": "[1142] إصدار الترخيص الصناعي",
      "price": 250,
      "category": "الوزارات / الصناعة",
      "active": true,
      "sale_ok": true
    },
    {
      "id": 2713,
      "name": "[1143] تجديد الترخيص الصناعي",
      "price": 250,
      "category": "الوزارات / الصناعة",
      "active": true,
      "sale_ok": true
    },
    {
      "id": 2714,
      "name": "[1144] ترقية الترخيص الصناعي",
      "price": 150,
      "category": "الوزارات / الصناعة",
      "active": true,
      "sale_ok": true
    },
    {
      "id": 2715,
      "name": "[1145] تأييد العمالة الوافدة",
      "price": 150,
      "category": "الوزارات / الصناعة",
      "active": true,
      "sale_ok": true
    },
    {
      "id": 2716,
      "name": "[1146] إصدار شهادة المنشأ",
      "price": 200,
      "category": "الوزارات / الصناعة",
      "active": true,
      "sale_ok": true
    },
    {
      "id": 2717,
      "name": "[1147] فسح استيراد المواد الكيميائية",
      "price": 200,
      "category": "الوزارات / الصناعة",
      "active": true,
      "sale_ok": true
    },
    {
      "id": 2718,
      "name": "[1148] إصدار وتجديد رخص الكشف التعديني",
      "price": 100,
      "category": "الوزارات / الصناعة",
      "active": true,
      "sale_ok": true
    },
    {
      "id": 2719,
      "name": "[1149] إصدار رخص استغلال المحاجر",
      "price": 100,
      "category": "الوزارات / الصناعة",
      "active": true,
      "sale_ok": true
    },
    {
      "id": 2720,
      "name": "[1150] تحويل الرخص التعدينية",
      "price": 80,
      "category": "الوزارات / الصناعة",
      "active": true,
      "sale_ok": true
    }
  ],
  "monshaat": [
    {
      "id": 2737,
      "name": "[1151] إصدار شهادة حجم المنشأة (منشآت)",
      "price": 135,
      "category": "خدمات حكومية / منشآت",
      "active": true,
      "sale_ok": true
    },
    {
      "id": 2738,
      "name": "[1152] إصدار رخص حاضنات الأعمال",
      "price": 300,
      "category": "خدمات حكومية / منشآت",
      "active": true,
      "sale_ok": true
    },
    {
      "id": 2739,
      "name": "[1154] التقديم على برامج دعم المنشآت",
      "price": 100,
      "category": "خدمات حكومية / منشآت",
      "active": true,
      "sale_ok": true
    },
    {
      "id": 2740,
      "name": "[1155] تسجيل المنشأة في منصة منشآت",
      "price": 100,
      "category": "خدمات حكومية / منشآت",
      "active": true,
      "sale_ok": true
    },
    {
      "id": 2741,
      "name": "[1156] تجديد شهادة حجم المنشأة",
      "price": 135,
      "category": "خدمات حكومية / منشآت",
      "active": true,
      "sale_ok": true
    }
  ],
  "mudad": [
    {
      "id": 2742,
      "name": "[1162] إضافة موظفين في مدد",
      "price": 99,
      "category": "خدمات حكومية / مدد",
      "active": true,
      "sale_ok": true
    }
  ],
  "mumaris": [
    {
      "id": 2743,
      "name": "[1164] التسجيل في ممارس بلس",
      "price": 49,
      "category": "خدمات حكومية / ممارس",
      "active": true,
      "sale_ok": true
    },
    {
      "id": 2744,
      "name": "[1165] استخراج رخصة التسجيل المهني",
      "price": 49,
      "category": "خدمات حكومية / ممارس",
      "active": true,
      "sale_ok": true
    },
    {
      "id": 2745,
      "name": "[1166] تجديد رخصة التسجيل المهني",
      "price": 49,
      "category": "خدمات حكومية / ممارس",
      "active": true,
      "sale_ok": true
    },
    {
      "id": 2746,
      "name": "[1167] التسجيل في اختبار الهيئة",
      "price": 49,
      "category": "خدمات حكومية / ممارس",
      "active": true,
      "sale_ok": true
    }
  ],
  "muqeem": [
    {
      "id": 2747,
      "name": "[1168] نقل كفالة",
      "price": 50,
      "category": "خدمات حكومية / مقيم",
      "active": true,
      "sale_ok": true
    },
    {
      "id": 2748,
      "name": "[1169] تجديد إقامة",
      "price": 50,
      "category": "خدمات حكومية / مقيم",
      "active": true,
      "sale_ok": true
    },
    {
      "id": 2749,
      "name": "[1170] تحديث معلومات جواز السفر",
      "price": 60,
      "category": "خدمات حكومية / مقيم",
      "active": true,
      "sale_ok": true
    },
    {
      "id": 2750,
      "name": "[1171] تصدير كشف بالموظفين المقيمين",
      "price": 75,
      "category": "خدمات حكومية / مقيم",
      "active": true,
      "sale_ok": true
    },
    {
      "id": 2751,
      "name": "[1172] إصدار تأشيرة خروج وعودة",
      "price": 33,
      "category": "خدمات حكومية / مقيم",
      "active": true,
      "sale_ok": true
    },
    {
      "id": 2752,
      "name": "[1173] إصدار تأشيرة خروج نهائي",
      "price": 50,
      "category": "خدمات حكومية / مقيم",
      "active": true,
      "sale_ok": true
    },
    {
      "id": 2753,
      "name": "[1174] طباعة تقرير مقيم",
      "price": 49,
      "category": "خدمات حكومية / مقيم",
      "active": true,
      "sale_ok": true
    }
  ],
  "musaned": [
    {
      "id": 2754,
      "name": "[1175] استخراج تأشيرات ذوي الإعاقة",
      "price": 99,
      "category": "خدمات حكومية / مساند",
      "active": true,
      "sale_ok": true
    },
    {
      "id": 2755,
      "name": "[1176] إصدار التأشيرات المنزلية",
      "price": 99,
      "category": "خدمات حكومية / مساند",
      "active": true,
      "sale_ok": true
    },
    {
      "id": 2756,
      "name": "[1178] تجديد عقد العمالة المنزلية",
      "price": 50,
      "category": "خدمات حكومية / مساند",
      "active": true,
      "sale_ok": true
    },
    {
      "id": 2757,
      "name": "[1179] نقل كفالة عامل منزلي",
      "price": 80,
      "category": "خدمات حكومية / مساند",
      "active": true,
      "sale_ok": true
    },
    {
      "id": 2758,
      "name": "[1180] تقديم بلاغ هروب عامل منزلي",
      "price": 60,
      "category": "خدمات حكومية / مساند",
      "active": true,
      "sale_ok": true
    }
  ],
  "najiz": [
    {
      "id": 2759,
      "name": "[1181] توثيق حضانة",
      "price": 50,
      "category": "خدمات حكومية / ناجز",
      "active": true,
      "sale_ok": true
    },
    {
      "id": 2760,
      "name": "[1182] حصر ورثة",
      "price": 100,
      "category": "خدمات حكومية / ناجز",
      "active": true,
      "sale_ok": true
    },
    {
      "id": 2761,
      "name": "[1183] إصدار صك ولاية على قاصر",
      "price": 100,
      "category": "خدمات حكومية / ناجز",
      "active": true,
      "sale_ok": true
    },
    {
      "id": 2762,
      "name": "[1184] إصدار شهادة وفاة لمواطن",
      "price": 50,
      "category": "خدمات حكومية / ناجز",
      "active": true,
      "sale_ok": true
    },
    {
      "id": 2763,
      "name": "[1185] صحيفة دعوى (فسخ عقد النكاح)",
      "price": 430,
      "category": "خدمات حكومية / ناجز",
      "active": true,
      "sale_ok": true
    },
    {
      "id": 2764,
      "name": "[1186] توثيق طلاق",
      "price": 50,
      "category": "خدمات حكومية / ناجز",
      "active": true,
      "sale_ok": true
    },
    {
      "id": 2765,
      "name": "[1187] إمهال تأجيل السداد",
      "price": 100,
      "category": "خدمات حكومية / ناجز",
      "active": true,
      "sale_ok": true
    },
    {
      "id": 2766,
      "name": "[1188] طباعة واستخراج الوثائق والصكوك",
      "price": 100,
      "category": "خدمات حكومية / ناجز",
      "active": true,
      "sale_ok": true
    },
    {
      "id": 2767,
      "name": "[1189] الرد على جميع القضايا",
      "price": 300,
      "category": "خدمات حكومية / ناجز",
      "active": true,
      "sale_ok": true
    },
    {
      "id": 2768,
      "name": "[1190] إصدار وكالة",
      "price": 30,
      "category": "خدمات حكومية / ناجز",
      "active": true,
      "sale_ok": true
    },
    {
      "id": 2769,
      "name": "[1191] رفع طلب تنفيذ",
      "price": 50,
      "category": "خدمات حكومية / ناجز",
      "active": true,
      "sale_ok": true
    },
    {
      "id": 2770,
      "name": "[1192] إنشاء عقد زواج",
      "price": 150,
      "category": "خدمات حكومية / ناجز",
      "active": true,
      "sale_ok": true
    },
    {
      "id": 2771,
      "name": "[1193] صحيفة دعوى (قضايا أسرية)",
      "price": 200,
      "category": "خدمات حكومية / ناجز",
      "active": true,
      "sale_ok": true
    },
    {
      "id": 2772,
      "name": "[1194] صحيفة دعوى (قضايا أخرى)",
      "price": 200,
      "category": "خدمات حكومية / ناجز",
      "active": true,
      "sale_ok": true
    },
    {
      "id": 2773,
      "name": "[1195] صحيفة دعوى (حق خاص)",
      "price": 200,
      "category": "خدمات حكومية / ناجز",
      "active": true,
      "sale_ok": true
    },
    {
      "id": 2774,
      "name": "[1196] صحيفة دعوى (مرورية)",
      "price": 200,
      "category": "خدمات حكومية / ناجز",
      "active": true,
      "sale_ok": true
    },
    {
      "id": 2775,
      "name": "[1197] رفع إيقاف خدمات في حال السداد",
      "price": 50,
      "category": "خدمات حكومية / ناجز",
      "active": true,
      "sale_ok": true
    },
    {
      "id": 2776,
      "name": "[1198] رفع طلب للتواصل العدل",
      "price": 100,
      "category": "خدمات حكومية / ناجز",
      "active": true,
      "sale_ok": true
    },
    {
      "id": 2777,
      "name": "[1199] استخراج صك حضانة",
      "price": 50,
      "category": "خدمات حكومية / ناجز",
      "active": true,
      "sale_ok": true
    },
    {
      "id": 2778,
      "name": "[1200] توثيق عقد زواج أو طلاق",
      "price": 50,
      "category": "خدمات حكومية / ناجز",
      "active": true,
      "sale_ok": true
    },
    {
      "id": 2779,
      "name": "[1201] استخراج صك حصر ورثة",
      "price": 120,
      "category": "خدمات حكومية / ناجز",
      "active": true,
      "sale_ok": true
    },
    {
      "id": 2780,
      "name": "[1202] طلب انهاء تنفيذ أو إمهال",
      "price": 50,
      "category": "خدمات حكومية / ناجز",
      "active": true,
      "sale_ok": true
    },
    {
      "id": 2781,
      "name": "[1203] تقديم طلب تنفيذ",
      "price": 50,
      "category": "خدمات حكومية / ناجز",
      "active": true,
      "sale_ok": true
    },
    {
      "id": 2782,
      "name": "[1204] إنشاء أو فسخ وكالة إلكترونية",
      "price": 50,
      "category": "خدمات حكومية / ناجز",
      "active": true,
      "sale_ok": true
    },
    {
      "id": 2783,
      "name": "[1205] إنشاء أو إلغاء سند لأمر",
      "price": 130,
      "category": "خدمات حكومية / ناجز",
      "active": true,
      "sale_ok": true
    },
    {
      "id": 2784,
      "name": "[1206] الإفراغ العقاري الإلكتروني",
      "price": 100,
      "category": "خدمات حكومية / ناجز",
      "active": true,
      "sale_ok": true
    },
    {
      "id": 2785,
      "name": "[1207] تحديث الصكوك العقارية",
      "price": 150,
      "category": "خدمات حكومية / ناجز",
      "active": true,
      "sale_ok": true
    },
    {
      "id": 2786,
      "name": "[1208] استخراج صك ولاية على قاصر سنا أو عقلا",
      "price": 100,
      "category": "خدمات حكومية / ناجز",
      "active": true,
      "sale_ok": true
    }
  ],
  "najm": [
    {
      "id": 2787,
      "name": "[1209] تقديم مطالبات نجم",
      "price": 100,
      "category": "خدمات حكومية / نجم",
      "active": true,
      "sale_ok": true
    },
    {
      "id": 2788,
      "name": "[1210] استعلام عن مطالبة",
      "price": 30,
      "category": "خدمات حكومية / نجم",
      "active": true,
      "sale_ok": true
    },
    {
      "id": 2789,
      "name": "[1211] مطالبة شركات التأمين بالحوادث",
      "price": 99,
      "category": "خدمات حكومية / نجم",
      "active": true,
      "sale_ok": true
    }
  ],
  "qawayem": [
    {
      "id": 2790,
      "name": "[1223] تسجيل المنشآت ومكاتب المراجعة",
      "price": 150,
      "category": "خدمات حكومية / قوائم",
      "active": true,
      "sale_ok": true
    },
    {
      "id": 2791,
      "name": "[1224] إيداع القوائم المالية المدققة",
      "price": 150,
      "category": "خدمات حكومية / قوائم",
      "active": true,
      "sale_ok": true
    },
    {
      "id": 2792,
      "name": "[1225] استعراض القوائم المالية",
      "price": 200,
      "category": "خدمات حكومية / قوائم",
      "active": true,
      "sale_ok": true
    },
    {
      "id": 2793,
      "name": "[1226] إصدار التقارير المالية والاقتصادية",
      "price": 200,
      "category": "خدمات حكومية / قوائم",
      "active": true,
      "sale_ok": true
    }
  ],
  "qiwa": [
    {
      "id": 2794,
      "name": "[1228] تسجيل نظام أجير",
      "price": 50,
      "category": "خدمات حكومية / قوى",
      "active": true,
      "sale_ok": true
    },
    {
      "id": 2795,
      "name": "[1231] توثيق عقد الموظفين",
      "price": 99,
      "category": "خدمات حكومية / قوى",
      "active": true,
      "sale_ok": true
    },
    {
      "id": 2796,
      "name": "[1235] بلاغ انقطاع عن العمل (بلاغ الهروب)",
      "price": 49,
      "category": "خدمات حكومية / قوى",
      "active": true,
      "sale_ok": true
    },
    {
      "id": 2797,
      "name": "[1237] إصدار تأشيرة عمل دائمة أو مؤقتة",
      "price": 99,
      "category": "خدمات حكومية / قوى",
      "active": true,
      "sale_ok": true
    }
  ],
  "realestate": [
    {
      "id": 2798,
      "name": "[1246] استخراج صك إلكتروني",
      "price": 100,
      "category": "خدمات حكومية / العقارات",
      "active": true,
      "sale_ok": true
    },
    {
      "id": 2799,
      "name": "[1247] إضافة أو رفع تقرير مساحي للأرض لغرض إصدار صك إلكتروني",
      "price": 150,
      "category": "خدمات حكومية / العقارات",
      "active": true,
      "sale_ok": true
    },
    {
      "id": 2800,
      "name": "[1248] الاستعلام عن صك عقاري",
      "price": 50,
      "category": "خدمات حكومية / العقارات",
      "active": true,
      "sale_ok": true
    },
    {
      "id": 2801,
      "name": "[1249] تسجيل عقار في البورصة العقارية",
      "price": 120,
      "category": "خدمات حكومية / العقارات",
      "active": true,
      "sale_ok": true
    }
  ],
  "saber": [
    {
      "id": 2802,
      "name": "[1250] تسجيل المنشأة وتحديث البيانات",
      "price": 100,
      "category": "خدمات حكومية / سابر",
      "active": true,
      "sale_ok": true
    },
    {
      "id": 2803,
      "name": "[1251] تصنيف المنتجات جمركياً",
      "price": 150,
      "category": "خدمات حكومية / سابر",
      "active": true,
      "sale_ok": true
    },
    {
      "id": 2804,
      "name": "[1252] إصدار شهادة مطابقة منتج",
      "price": 250,
      "category": "خدمات حكومية / سابر",
      "active": true,
      "sale_ok": true
    },
    {
      "id": 2805,
      "name": "[1253] إصدار شهادة مطابقة إرسالية",
      "price": 200,
      "category": "خدمات حكومية / سابر",
      "active": true,
      "sale_ok": true
    },
    {
      "id": 2806,
      "name": "[1254] تسجيل المنتجات الغير خاضعة للوائح",
      "price": 120,
      "category": "خدمات حكومية / سابر",
      "active": true,
      "sale_ok": true
    },
    {
      "id": 2807,
      "name": "[1255] إصدار شهادات مطابقة للمنتجات المحلية",
      "price": 300,
      "category": "خدمات حكومية / سابر",
      "active": true,
      "sale_ok": true
    },
    {
      "id": 2808,
      "name": "[1256] إصدار شهادات الإعفاء",
      "price": 175,
      "category": "خدمات حكومية / سابر",
      "active": true,
      "sale_ok": true
    },
    {
      "id": 2809,
      "name": "[1257] دراسة متطلبات المنتج قبل الشراء",
      "price": 200,
      "category": "خدمات حكومية / سابر",
      "active": true,
      "sale_ok": true
    }
  ],
  "sakani": [
    {
      "id": 2810,
      "name": "[1258] الاستعلام عن حالة الأهلية",
      "price": 50,
      "category": "خدمات حكومية / سكني",
      "active": true,
      "sale_ok": true
    },
    {
      "id": 2811,
      "name": "[1259] إصدار شهادة إعفاء من ضريبة المسكن الأول",
      "price": 50,
      "category": "خدمات حكومية / سكني",
      "active": true,
      "sale_ok": true
    },
    {
      "id": 2812,
      "name": "[1260] التقديم على حجز أرض مجانية في سكني",
      "price": 99,
      "category": "خدمات حكومية / سكني",
      "active": true,
      "sale_ok": true
    },
    {
      "id": 2813,
      "name": "[1261] تسجيل في مستشارك العقاري",
      "price": 100,
      "category": "خدمات حكومية / سكني",
      "active": true,
      "sale_ok": true
    }
  ],
  "salama": [
    {
      "id": 2814,
      "name": "[1262] إصدار شهادة تركيب أدوات السلامة",
      "price": 150,
      "category": "خدمات حكومية / سلامة",
      "active": true,
      "sale_ok": true
    },
    {
      "id": 2815,
      "name": "[1263] إصدار ترخيص الدفاع المدني",
      "price": 200,
      "category": "خدمات حكومية / سلامة",
      "active": true,
      "sale_ok": true
    },
    {
      "id": 2816,
      "name": "[1264] إصدار رخصة سلامة جديدة",
      "price": 250,
      "category": "خدمات حكومية / سلامة",
      "active": true,
      "sale_ok": true
    },
    {
      "id": 2817,
      "name": "[1265] تجديد رخصة سلامة",
      "price": 150,
      "category": "خدمات حكومية / سلامة",
      "active": true,
      "sale_ok": true
    },
    {
      "id": 2818,
      "name": "[1266] إصدار تراخيص سلامة مؤقتة",
      "price": 100,
      "category": "خدمات حكومية / سلامة",
      "active": true,
      "sale_ok": true
    },
    {
      "id": 2819,
      "name": "[1267] الاستعلام عن التراخيص وتتبع الطلبات",
      "price": 50,
      "category": "خدمات حكومية / سلامة",
      "active": true,
      "sale_ok": true
    },
    {
      "id": 2820,
      "name": "[1268] إدارة عقود الصيانة السنوية وشهادة الفحص",
      "price": 300,
      "category": "خدمات حكومية / سلامة",
      "active": true,
      "sale_ok": true
    }
  ],
  "sbc": [
    {
      "id": 2821,
      "name": "[1271] إصدار السجل التجاري للمؤسسات",
      "price": 100,
      "category": "خدمات حكومية / المركز السعودي للأعمال",
      "active": true,
      "sale_ok": true
    },
    {
      "id": 2822,
      "name": "[1272] حجز / تمديد / إلغاء اسم تجاري",
      "price": 30,
      "category": "خدمات حكومية / المركز السعودي للأعمال",
      "active": true,
      "sale_ok": true
    },
    {
      "id": 2823,
      "name": "[1274] تحويل مؤسسة إلى شركة",
      "price": 750,
      "category": "خدمات حكومية / المركز السعودي للأعمال",
      "active": true,
      "sale_ok": true
    },
    {
      "id": 2824,
      "name": "[1278] شطب سجل تجاري (شركة ذات شخص واحد)",
      "price": 400,
      "category": "خدمات حكومية / المركز السعودي للأعمال",
      "active": true,
      "sale_ok": true
    },
    {
      "id": 2825,
      "name": "[1281] التسجيل في تاي أو تمارا",
      "price": 75,
      "category": "خدمات حكومية / المركز السعودي للأعمال",
      "active": true,
      "sale_ok": true
    }
  ],
  "individuals": [
    {
      "id": 2679,
      "name": "[1279] الاستعلام عن السجلات التجارية على اسمك",
      "price": 25.8,
      "category": "خدمات الأفراد / الأفراد",
      "active": true,
      "sale_ok": true
    },
    {
      "id": 2680,
      "name": "[1283] إفادة بعدم وجود سجل تجاري",
      "price": 50,
      "category": "خدمات الأفراد / الأفراد",
      "active": true,
      "sale_ok": true
    }
  ],
  "sce": [
    {
      "id": 2826,
      "name": "[1286] إصدار عضوية الهيئة السعودية للمهندسين",
      "price": 100,
      "category": "خدمات حكومية / هيئة المهندسين",
      "active": true,
      "sale_ok": true
    },
    {
      "id": 2827,
      "name": "[1287] تجديد عضوية الهيئة السعودية للمهندسين",
      "price": 100,
      "category": "خدمات حكومية / هيئة المهندسين",
      "active": true,
      "sale_ok": true
    },
    {
      "id": 2828,
      "name": "[1288] الاستعلام عن الترخيص المهني",
      "price": 50,
      "category": "خدمات حكومية / هيئة المهندسين",
      "active": true,
      "sale_ok": true
    },
    {
      "id": 2829,
      "name": "[1289] تحديث البيانات المهنية",
      "price": 60,
      "category": "خدمات حكومية / هيئة المهندسين",
      "active": true,
      "sale_ok": true
    }
  ],
  "seza": [
    {
      "id": 2830,
      "name": "[1290] تسجيل رخصة استثمارية",
      "price": 350,
      "category": "خدمات حكومية / سيزا",
      "active": true,
      "sale_ok": true
    },
    {
      "id": 2831,
      "name": "[1291] تقديم طلب تصريح تشغيل",
      "price": 350,
      "category": "خدمات حكومية / سيزا",
      "active": true,
      "sale_ok": true
    },
    {
      "id": 2832,
      "name": "[1292] تجديد تصريح التشغيل",
      "price": 200,
      "category": "خدمات حكومية / سيزا",
      "active": true,
      "sale_ok": true
    },
    {
      "id": 2833,
      "name": "[1293] إصدار تصريح أشغال",
      "price": 200,
      "category": "خدمات حكومية / سيزا",
      "active": true,
      "sale_ok": true
    },
    {
      "id": 2834,
      "name": "[1294] تصريح أشغال الهياكل المؤقتة",
      "price": 150,
      "category": "خدمات حكومية / سيزا",
      "active": true,
      "sale_ok": true
    },
    {
      "id": 2835,
      "name": "[1295] إصدار ترخيص تأهيل واعتماد المطورين",
      "price": 150,
      "category": "خدمات حكومية / سيزا",
      "active": true,
      "sale_ok": true
    }
  ],
  "shomoos": [
    {
      "id": 2836,
      "name": "[1296] تسجيل في نظام شموس (منشأة/فرع)",
      "price": 100,
      "category": "خدمات حكومية / شموس",
      "active": true,
      "sale_ok": true
    },
    {
      "id": 2837,
      "name": "[1297] نظام شموس إدارة المستخدمين (إضافة/حذف)",
      "price": 50,
      "category": "خدمات حكومية / شموس",
      "active": true,
      "sale_ok": true
    },
    {
      "id": 2838,
      "name": "[1298] تحديث بيانات المنشأة في شموس",
      "price": 60,
      "category": "خدمات حكومية / شموس",
      "active": true,
      "sale_ok": true
    },
    {
      "id": 2839,
      "name": "[1299] استخراج تقرير الحضور والغياب",
      "price": 80,
      "category": "خدمات حكومية / شموس",
      "active": true,
      "sale_ok": true
    }
  ],
  "simah": [
    {
      "id": 2840,
      "name": "[1300] طلب تقرير سمة",
      "price": 99,
      "category": "خدمات حكومية / سمة",
      "active": true,
      "sale_ok": true
    },
    {
      "id": 2841,
      "name": "[1301] طلب رفع تعثر",
      "price": 99,
      "category": "خدمات حكومية / سمة",
      "active": true,
      "sale_ok": true
    },
    {
      "id": 2842,
      "name": "[1302] اعتراض على منتج متعثر",
      "price": 99,
      "category": "خدمات حكومية / سمة",
      "active": true,
      "sale_ok": true
    }
  ],
  "spl": [
    {
      "id": 2843,
      "name": "[1303] تسجيل عنوان وطني للأفراد",
      "price": 50,
      "category": "خدمات حكومية / سبل",
      "active": true,
      "sale_ok": true
    },
    {
      "id": 2844,
      "name": "[1305] تسجيل عنوان تابع قاصر",
      "price": 50,
      "category": "خدمات حكومية / سبل",
      "active": true,
      "sale_ok": true
    },
    {
      "id": 2845,
      "name": "[1306] تحديث العنوان الوطني",
      "price": 35,
      "category": "خدمات حكومية / سبل",
      "active": true,
      "sale_ok": true
    },
    {
      "id": 2846,
      "name": "[1307] طباعة العنوان الوطني",
      "price": 35,
      "category": "خدمات حكومية / سبل",
      "active": true,
      "sale_ok": true
    }
  ],
  "tam": [
    {
      "id": 2855,
      "name": "[1308] إصدار رخصة سير مركبة",
      "price": 80,
      "category": "خدمات حكومية / تام",
      "active": true,
      "sale_ok": true
    },
    {
      "id": 2856,
      "name": "[1309] تجديد رخصة سير مركبة",
      "price": 80,
      "category": "خدمات حكومية / تام",
      "active": true,
      "sale_ok": true
    },
    {
      "id": 2857,
      "name": "[1310] نقل ملكية مركبة",
      "price": 60,
      "category": "خدمات حكومية / تام",
      "active": true,
      "sale_ok": true
    },
    {
      "id": 2858,
      "name": "[1311] إصدار لوحات مركبة",
      "price": 60,
      "category": "خدمات حكومية / تام",
      "active": true,
      "sale_ok": true
    },
    {
      "id": 2859,
      "name": "[1312] إصدار تفويض داخلي",
      "price": 150,
      "category": "خدمات حكومية / تام",
      "active": true,
      "sale_ok": true
    },
    {
      "id": 2860,
      "name": "[1313] إصدار تفويض خارجي",
      "price": 150,
      "category": "خدمات حكومية / تام",
      "active": true,
      "sale_ok": true
    },
    {
      "id": 2861,
      "name": "[1314] إلغاء تفويض مركبة",
      "price": 100,
      "category": "خدمات حكومية / تام",
      "active": true,
      "sale_ok": true
    },
    {
      "id": 2862,
      "name": "[1315] إضافة مستخدم فعلي للمركبة",
      "price": 100,
      "category": "خدمات حكومية / تام",
      "active": true,
      "sale_ok": true
    },
    {
      "id": 2863,
      "name": "[1316] الاستعلام عن مخالفات المركبة",
      "price": 70,
      "category": "خدمات حكومية / تام",
      "active": true,
      "sale_ok": true
    },
    {
      "id": 2864,
      "name": "[1317] الاستعلام عن وثائق التأمين",
      "price": 70,
      "category": "خدمات حكومية / تام",
      "active": true,
      "sale_ok": true
    },
    {
      "id": 2865,
      "name": "[1318] الاستعلام عن الفحص الدوري للمركبة",
      "price": 100,
      "category": "خدمات حكومية / تام",
      "active": true,
      "sale_ok": true
    },
    {
      "id": 2866,
      "name": "[1319] الاستعلام عن تفاصيل المركبة",
      "price": 100,
      "category": "خدمات حكومية / تام",
      "active": true,
      "sale_ok": true
    },
    {
      "id": 2867,
      "name": "[1320] تحديث بيانات التأمين",
      "price": 50,
      "category": "خدمات حكومية / تام",
      "active": true,
      "sale_ok": true
    }
  ],
  "taqat": [
    {
      "id": 2868,
      "name": "[1321] تقديم دعم المنشآت",
      "price": 50,
      "category": "خدمات حكومية / طاقات",
      "active": true,
      "sale_ok": true
    },
    {
      "id": 2869,
      "name": "[1322] تسجيل حساب في طاقات",
      "price": 100,
      "category": "خدمات حكومية / طاقات",
      "active": true,
      "sale_ok": true
    },
    {
      "id": 2870,
      "name": "[1323] اعتراض على دفعة ناقصة أو لم تسلم",
      "price": 50,
      "category": "خدمات حكومية / طاقات",
      "active": true,
      "sale_ok": true
    },
    {
      "id": 2871,
      "name": "[1324] تسجيل في إعانة البحث عن عمل",
      "price": 150,
      "category": "خدمات حكومية / طاقات",
      "active": true,
      "sale_ok": true
    }
  ],
  "ministry-hr": [
    {
      "id": 2710,
      "name": "[1325] تسجيل في دعم توطين",
      "price": 0,
      "category": "الوزارات / الموارد البشرية",
      "active": true,
      "sale_ok": true
    },
    {
      "id": 2707,
      "name": "[1447] فتح حساب مستخدم منشأة على وزارة الموارد",
      "price": 0,
      "category": "الوزارات / الموارد البشرية",
      "active": true,
      "sale_ok": true
    },
    {
      "id": 2708,
      "name": "[1448] استخراج نسخة إلكترونية لشهادة من وزارة الموارد البشرية - اعمال",
      "price": 0,
      "category": "الوزارات / الموارد البشرية",
      "active": true,
      "sale_ok": true
    },
    {
      "id": 2709,
      "name": "[1449] فتح حساب على برنامج العمل عن بعد التابع لوزارة الموارد البشرية والتنمية",
      "price": 0,
      "category": "الوزارات / الموارد البشرية",
      "active": true,
      "sale_ok": true
    },
    {
      "id": 2711,
      "name": "[1605] رفع دعوى بالتسوية الودية (شكوى عمالية)",
      "price": 0,
      "category": "الوزارات / الموارد البشرية",
      "active": true,
      "sale_ok": true
    }
  ],
  "taqyees": [
    {
      "id": 2872,
      "name": "[1329] تسجيل حساب منشأة في تقييس",
      "price": 100,
      "category": "خدمات حكومية / تقييس",
      "active": true,
      "sale_ok": true
    },
    {
      "id": 2873,
      "name": "[1330] طلب التحقق الدوري",
      "price": 100,
      "category": "خدمات حكومية / تقييس",
      "active": true,
      "sale_ok": true
    },
    {
      "id": 2874,
      "name": "[1331] طلب التحقق الأولي",
      "price": 150,
      "category": "خدمات حكومية / تقييس",
      "active": true,
      "sale_ok": true
    },
    {
      "id": 2875,
      "name": "[1332] طلب التحقق بعد الصيانة",
      "price": 150,
      "category": "خدمات حكومية / تقييس",
      "active": true,
      "sale_ok": true
    },
    {
      "id": 2876,
      "name": "[1333] طلب شهادة اعتماد الطراز",
      "price": 200,
      "category": "خدمات حكومية / تقييس",
      "active": true,
      "sale_ok": true
    },
    {
      "id": 2877,
      "name": "[1334] طلب تأهيل جهة التحقق",
      "price": 200,
      "category": "خدمات حكومية / تقييس",
      "active": true,
      "sale_ok": true
    },
    {
      "id": 2878,
      "name": "[1335] طلب إذن صيانة",
      "price": 150,
      "category": "خدمات حكومية / تقييس",
      "active": true,
      "sale_ok": true
    },
    {
      "id": 2879,
      "name": "[1336] الاستعلام عن حالة طلب",
      "price": 150,
      "category": "خدمات حكومية / تقييس",
      "active": true,
      "sale_ok": true
    }
  ],
  "taradhi": [
    {
      "id": 2880,
      "name": "[1337] تقديم طلب صلح",
      "price": 50,
      "category": "خدمات حكومية / تراضي",
      "active": true,
      "sale_ok": true
    },
    {
      "id": 2881,
      "name": "[1338] طباعة وثيقة صلح",
      "price": 20,
      "category": "خدمات حكومية / تراضي",
      "active": true,
      "sale_ok": true
    },
    {
      "id": 2882,
      "name": "[1339] متابعة طلب صلح",
      "price": 30,
      "category": "خدمات حكومية / تراضي",
      "active": true,
      "sale_ok": true
    },
    {
      "id": 2883,
      "name": "[1340] الاستعلام عن طلب تراضي",
      "price": 20,
      "category": "خدمات حكومية / تراضي",
      "active": true,
      "sale_ok": true
    }
  ],
  "telecom": [
    {
      "id": 2884,
      "name": "[1341] تأسيس شريحة اتصال (SIM)",
      "price": 80,
      "category": "خدمات حكومية / الاتصالات",
      "active": true,
      "sale_ok": true
    },
    {
      "id": 2885,
      "name": "[1342] تأسيس خط إنترنت للمنشآت",
      "price": 100,
      "category": "خدمات حكومية / الاتصالات",
      "active": true,
      "sale_ok": true
    },
    {
      "id": 2886,
      "name": "[1343] تأسيس خط هاتف أرضي",
      "price": 80,
      "category": "خدمات حكومية / الاتصالات",
      "active": true,
      "sale_ok": true
    },
    {
      "id": 2887,
      "name": "[1344] تقديم اعتراض على فاتورة",
      "price": 60,
      "category": "خدمات حكومية / الاتصالات",
      "active": true,
      "sale_ok": true
    },
    {
      "id": 2888,
      "name": "[1345] دراسة احتياجات المؤسسة من خدمات الاتصال والإنترنت",
      "price": 150,
      "category": "خدمات حكومية / الاتصالات",
      "active": true,
      "sale_ok": true
    }
  ],
  "water": [
    {
      "id": 2889,
      "name": "[1346] نقل ملكية عداد المياه",
      "price": 50,
      "category": "خدمات حكومية / المياه",
      "active": true,
      "sale_ok": true
    },
    {
      "id": 2890,
      "name": "[1347] توثيق حساب عداد المياه",
      "price": 50,
      "category": "خدمات حكومية / المياه",
      "active": true,
      "sale_ok": true
    },
    {
      "id": 2891,
      "name": "[1348] إلغاء حساب شركة المياه",
      "price": 50,
      "category": "خدمات حكومية / المياه",
      "active": true,
      "sale_ok": true
    }
  ],
  "business-closure": [
    {
      "id": 2530,
      "name": "[1351] إلغاء الرقم المميز",
      "price": 100,
      "category": "خدمات الأعمال / إغلاق",
      "active": true,
      "sale_ok": true
    },
    {
      "id": 2525,
      "name": "[955] افادة بعدم وجود سجل تجاري",
      "price": 20,
      "category": "خدمات الأعمال / إغلاق",
      "active": true,
      "sale_ok": true
    },
    {
      "id": 2526,
      "name": "[956] طباعة شهادة شطب سجل تجاري",
      "price": 20,
      "category": "خدمات الأعمال / إغلاق",
      "active": true,
      "sale_ok": true
    },
    {
      "id": 2527,
      "name": "[957] إغلاق المنشأة",
      "price": 20,
      "category": "خدمات الأعمال / إغلاق",
      "active": true,
      "sale_ok": true
    },
    {
      "id": 2528,
      "name": "[958] الغاء رخصة بلدي",
      "price": 20,
      "category": "خدمات الأعمال / إغلاق",
      "active": true,
      "sale_ok": true
    },
    {
      "id": 2529,
      "name": "[959] شطب السجل التجاري للمؤسسات",
      "price": 100,
      "category": "خدمات الأعمال / إغلاق",
      "active": true,
      "sale_ok": true
    }
  ],
  "zatca": [
    {
      "id": 2892,
      "name": "[1352] طباعة الشهادة الضريبية وشهادة الزكاة والدخل",
      "price": 49,
      "category": "خدمات حكومية / زكاة وضريبة",
      "active": true,
      "sale_ok": true
    }
  ],
  "ministry-education": [
    {
      "id": 2696,
      "name": "[1435] تسجيل الطالب في رياض الأطفال",
      "price": 0,
      "category": "الوزارات / التعليم",
      "active": true,
      "sale_ok": true
    }
  ],
  "ministry-environment": [
    {
      "id": 2697,
      "name": "[1437] طلب تفعيل بطاقة صحية",
      "price": 0,
      "category": "الوزارات / البيئة",
      "active": true,
      "sale_ok": true
    },
    {
      "id": 2698,
      "name": "[1594] طلب فتح بطاقة صحية",
      "price": 0,
      "category": "الوزارات / البيئة",
      "active": true,
      "sale_ok": true
    }
  ],
  "ministry-foreign": [
    {
      "id": 2699,
      "name": "[1439] طلب زيارة عائلية",
      "price": 0,
      "category": "الوزارات / الخارجية",
      "active": true,
      "sale_ok": true
    },
    {
      "id": 2702,
      "name": "[1442] تصديق الوكالات الخارجية",
      "price": 0,
      "category": "الوزارات / الخارجية",
      "active": true,
      "sale_ok": true
    },
    {
      "id": 2703,
      "name": "[1443] استعلام عن طلب زيارة",
      "price": 0,
      "category": "الوزارات / الخارجية",
      "active": true,
      "sale_ok": true
    },
    {
      "id": 2704,
      "name": "[1444] تفويض تأشيرات عمل",
      "price": 0,
      "category": "الوزارات / الخارجية",
      "active": true,
      "sale_ok": true
    },
    {
      "id": 2700,
      "name": "[1595] تقديم طلب زيارة عائلية للمقيمين",
      "price": 0,
      "category": "الوزارات / الخارجية",
      "active": true,
      "sale_ok": true
    },
    {
      "id": 2701,
      "name": "[1596] تقديم طلب زيارة شخصية للمواطنين",
      "price": 0,
      "category": "الوزارات / الخارجية",
      "active": true,
      "sale_ok": true
    },
    {
      "id": 2705,
      "name": "[1600] تفويض تأشيرات العمل",
      "price": 0,
      "category": "الوزارات / الخارجية",
      "active": true,
      "sale_ok": true
    },
    {
      "id": 2706,
      "name": "[1601] طلب زيارة عمل",
      "price": 0,
      "category": "الوزارات / الخارجية",
      "active": true,
      "sale_ok": true
    }
  ],
  "ministry-investment": [
    {
      "id": 2721,
      "name": "[1452] إصدار ترخيص وزارة الاستثمار",
      "price": 0,
      "category": "الوزارات / الاستثمار",
      "active": true,
      "sale_ok": true
    },
    {
      "id": 2722,
      "name": "[1453] خدمة تجديد ترخيص وزارة الاستثمار",
      "price": 0,
      "category": "الوزارات / الاستثمار",
      "active": true,
      "sale_ok": true
    },
    {
      "id": 2724,
      "name": "[1455] متابعة طلبات الاستثمار",
      "price": 0,
      "category": "الوزارات / الاستثمار",
      "active": true,
      "sale_ok": true
    },
    {
      "id": 2726,
      "name": "[1457] إلغاء ترخيص الاستثمار",
      "price": 0,
      "category": "الوزارات / الاستثمار",
      "active": true,
      "sale_ok": true
    },
    {
      "id": 2723,
      "name": "[1607] خدمة تعديل ترخيص وزارة الاستثمار",
      "price": 0,
      "category": "الوزارات / الاستثمار",
      "active": true,
      "sale_ok": true
    },
    {
      "id": 2725,
      "name": "[1609] مراجعة متطلبات النشاطات قبل التقديم",
      "price": 0,
      "category": "الوزارات / الاستثمار",
      "active": true,
      "sale_ok": true
    }
  ],
  "ministry-justice": [
    {
      "id": 2727,
      "name": "[1458] خدمة الاستعلام عن طلبات التنفيذ",
      "price": 0,
      "category": "الوزارات / العدل",
      "active": true,
      "sale_ok": true
    },
    {
      "id": 2729,
      "name": "[1460] تقديم دعوى مالية",
      "price": 0,
      "category": "الوزارات / العدل",
      "active": true,
      "sale_ok": true
    },
    {
      "id": 2730,
      "name": "[1461] دعوى محكمة عالمية",
      "price": 0,
      "category": "الوزارات / العدل",
      "active": true,
      "sale_ok": true
    },
    {
      "id": 2731,
      "name": "[1462] حجز المواعيد في المحكمة",
      "price": 0,
      "category": "الوزارات / العدل",
      "active": true,
      "sale_ok": true
    },
    {
      "id": 2732,
      "name": "[1463] تقديم دعوى زيارة - تنظيم حقوق زيارة الأبناء",
      "price": 0,
      "category": "الوزارات / العدل",
      "active": true,
      "sale_ok": true
    },
    {
      "id": 2728,
      "name": "[1611] إصدار والغاء الوكالات الشرعية",
      "price": 0,
      "category": "الوزارات / العدل",
      "active": true,
      "sale_ok": true
    }
  ],
  "ministry-labor": [
    {
      "id": 2733,
      "name": "[1464] اعتراض على غرامة تفتيش",
      "price": 0,
      "category": "الوزارات / العمل",
      "active": true,
      "sale_ok": true
    },
    {
      "id": 2734,
      "name": "[1465] نقل ملكية ملفات مكتب العمل",
      "price": 0,
      "category": "الوزارات / العمل",
      "active": true,
      "sale_ok": true
    },
    {
      "id": 2735,
      "name": "[1466] شطب ملفات مكتب العمل",
      "price": 0,
      "category": "الوزارات / العمل",
      "active": true,
      "sale_ok": true
    },
    {
      "id": 2736,
      "name": "[1618] خدمة تحديث بيانات العمالة",
      "price": 0,
      "category": "الوزارات / العمل",
      "active": true,
      "sale_ok": true
    }
  ],
  "support-hafiz": [
    {
      "id": 2849,
      "name": "[1470] تسجيل في دعم حافز",
      "price": 0,
      "category": "برامج الدعم / حافز",
      "active": true,
      "sale_ok": true
    }
  ],
  "support-sanad": [
    {
      "id": 2850,
      "name": "[1471] استعلام استحقاقك دعم ساند",
      "price": 0,
      "category": "برامج الدعم / ساند",
      "active": true,
      "sale_ok": true
    },
    {
      "id": 2851,
      "name": "[1472] التسجيل في دعم ساند",
      "price": 0,
      "category": "برامج الدعم / ساند",
      "active": true,
      "sale_ok": true
    }
  ],
  "support-tamheer": [
    {
      "id": 2852,
      "name": "[1473] تسجيل في تمهير",
      "price": 0,
      "category": "برامج الدعم / تمهير",
      "active": true,
      "sale_ok": true
    }
  ],
  "support-women": [
    {
      "id": 2853,
      "name": "[1474] التقديم على دعم نقل المرأة العاملة وصول",
      "price": 0,
      "category": "برامج الدعم / المرأة",
      "active": true,
      "sale_ok": true
    },
    {
      "id": 2854,
      "name": "[1475] التقديم على دعم المرأة العاملة في برنامج قرة",
      "price": 0,
      "category": "برامج الدعم / المرأة",
      "active": true,
      "sale_ok": true
    }
  ],
  "support-guarantee": [
    {
      "id": 2848,
      "name": "[1620] خدمات الضمان المطور",
      "price": 0,
      "category": "برامج الدعم / الضمان المطور",
      "active": true,
      "sale_ok": true
    }
  ],
  "support-citizen": [
    {
      "id": 2847,
      "name": "[1653] خدمات حساب المواطن",
      "price": 0,
      "category": "برامج الدعم / حساب المواطن",
      "active": true,
      "sale_ok": true
    }
  ],
  "packages": [
    {
      "id": 2912,
      "name": "[PKG-BIZ-L] باقة إدارة المنشآت — 11  إلى 20  موظفاً",
      "price": 1990,
      "category": "باقات الاشتراك / إدارة المنشآت",
      "active": true,
      "sale_ok": true
    },
    {
      "id": 2911,
      "name": "[PKG-BIZ-M] باقة إدارة المنشآت — 6  إلى 10  موظفين",
      "price": 1490,
      "category": "باقات الاشتراك / إدارة المنشآت",
      "active": true,
      "sale_ok": true
    },
    {
      "id": 2910,
      "name": "[PKG-BIZ-S] باقة إدارة المنشآت — 1  إلى 5  موظفين",
      "price": 990,
      "category": "باقات الاشتراك / إدارة المنشآت",
      "active": true,
      "sale_ok": true
    },
    {
      "id": 2913,
      "name": "[PKG-BIZ-XL] باقة إدارة المنشآت — 21  إلى 30  موظفاً",
      "price": 2490,
      "category": "باقات الاشتراك / إدارة المنشآت",
      "active": true,
      "sale_ok": true
    },
    {
      "id": 2907,
      "name": "[PKG-BRONZE] الباقة البرونزية — 10  خدمات شهرياً",
      "price": 620,
      "category": "باقات الاشتراك / الاشتراكات الشهرية",
      "active": true,
      "sale_ok": true
    },
    {
      "id": 2909,
      "name": "[PKG-GOLD] الباقة الذهبية — 50  خدمة شهرياً",
      "price": 3150,
      "category": "باقات الاشتراك / الاشتراكات الشهرية",
      "active": true,
      "sale_ok": true
    },
    {
      "id": 2908,
      "name": "[PKG-SILVER] الباقة الفضية — 25  خدمة شهرياً",
      "price": 1500,
      "category": "باقات الاشتراك / الاشتراكات الشهرية",
      "active": true,
      "sale_ok": true
    }
  ]
}